[

         {

                 	"name": "Palace",
           
	              	"isNationalWonder": true,
           
	              	"production": 3,
           
	              	"science": 3,
           
              		"gold": 3,
            
              		"culture": 1,
           
              		"cityStrength": 0,
           
	              	"cost": 1,
           
               		"uniques": ["Indicates the capital city"],

         },

         {

                  "name": "Monument",
           
              		"culture": 2,
                   
              		"cost": 60,
           
              		"hurryCostModifier": 40,
           
              		"maintenance": 1,
           
              		"uniques": ["[-20]% Culture cost of natural border growth [in this city]"]
           
         },

         {

		 "name": "Basic Housing I",

		 "food": 1,

		 "happiness": 2,

		 "cost": 35,

		 "hurryCostModifier": 35

		 "maintenance": 1,

		 "uniques": ["[+20]% Yield from every [Farm]"]

	 },

         {

		 "name": "Wooden Harbor",

		 "production": 1,

		 "Gold": 1,

		 "cost": 45,

		 "hurryCostModifier": 45,

		 "maintenance": 1,

		 "uniques": ["Must be next to [Coast]","[+20]% Yield from every [Work Boats]","[+1 Gold] <after discovering [Sailing]>"],

		 "requiredTech": "Construction",

	 },

	 {

		 "name": "Crafting Area",

		 "production": 2,

		 "cost": 35,

		 "hurryCostModifier": 35,

		 "maintenance": 1,

		 "requiredTech": "Construction",

	 },

	 {

		 "name": "Entertainment Area",

		 "happiness": 3,

		 "cost": 50,

		 "hurryCostModifier": 50,

		 "maintenance": 1,

		 "requiredTech": "Construction",

	 },	 
		 

         {

		 "name": "Basic Housing II",

		 "food": 1,

		 "happiness": 2,

		 "cost": 35,

		 "hurryCostModifier": 35,

		 "maintenance": 2,

		 "uniques": ["[+10]% Yield from every [Farm]"],

		 "requiredTech": "Basic Sheltering",

	 },

         {

		 "name": "Basic Housing III",

		 "food": 1,

		 "happiness": 2,

		 "cost": 60,

		 "hurryCostModifier": 60,

		 "maintenance": 2,

		 "uniques": ["[+10]% Yield from every [Pasture]"]

		 "requiredTech": "Construction",

	 },

         {
		 
		"name": "Market",
	
		"gold": 1,

	        "production": 1,

	        "food": 1,
	
		"cost": 80,
	
		"percentStatBonus": {"gold": 25},
	
		"requiredTech": "Trading",
		 
	},

	{
		"name": "Shrine",
		
		"faith": 2,
		
		"cost": 40,
		
		"maintenance": 1,
		
		"requiredTech": "Basic Sheltering",
		
		"uniques": ["Hidden when religion is disabled"]
		
	},

	{
		"name": "Stepping Stones to God",
		
		"faith": 5,

		"cost": 80,
		
		"isWonder": true,

		"requiredTech": "Construction",
		
		"quote": "'Time crumbles things; everything grows old and is forgotten under the power of time' - Aristotle"
	},

]
