[

        {

		                "name": "Agriculture"

		                "row": 3,

		                "quote": "'' -.",

		                "uniques": ["Starting tech"],

	                },
	
         {

                  "columnNumber": 0,
           
		"era": "Creation Era",
           
		"techCost": 20,
           
		"buildingCost": 40,
           
		"techs": [
      
			{
              
			        "name": "Fish Catching",
        
		         	"row": 1,
        
		                "quote": "Fish!.' - Unknown",

			},

		        {

				"name": "Farming",

				"row": 3,

				"quote": "'' -",


			},

		        {

				"name": "Hunting",

				"row": 5,

				"quote": "'' -.",

			},

			{

				"name": "Mining",

				"row": 9,

				"quote": "'' -.",

			},

		]
		 
	 },

]
			

         


